[
    {
        "hastaID": 51,
        "hastaAdi": "Ümmet",
        "hastaSoyadi": "Arsoy",
        "hastaCinsiyet": "Kadın",
        "hastaTarih": "2005-11-21",
        "hastaTelefon": "+90(682)6645648",
        "hastaAdres": "13271 Akdeniz Roads\nEast Zahid, AZ 17434",
        "hastaSifre": "tphfw"
    },
    {
        "hastaID": 52,
        "hastaAdi": "Talayer",
        "hastaSoyadi": "Akça",
        "hastaCinsiyet": "Kadın",
        "hastaTarih": "1962-08-16",
        "hastaTelefon": "+90(902)6823941",
        "hastaAdres": "2376 Örfiye Manors\nEast Gülçe, VT 33749",
        "hastaSifre": "bqtla"
    },
    {
        "hastaID": 53,
        "hastaAdi": "Ferinaz",
        "hastaSoyadi": "Arsoy",
        "hastaCinsiyet": "Kadın",
        "hastaTarih": "1963-02-25",
        "hastaTelefon": "0033-544 3257",
        "hastaAdres": "2682 Kılıçbay Lodge\nNorth Tuğtaşland, AZ 42778",
        "hastaSifre": "qagkx"
    },
    {
        "hastaID": 54,
        "hastaAdi": "Bahaddin",
        "hastaSoyadi": "Korutürk",
        "hastaCinsiyet": "Erkek",
        "hastaTarih": "2008-04-04",
        "hastaTelefon": "(576)413 1582",
        "hastaAdres": "594 Manço Field\nSouth Mahsun, NJ 91575",
        "hastaSifre": "19nnn"
    },
    {
        "hastaID": 55,
        "hastaAdi": "Yıldız",
        "hastaSoyadi": "Akgündüz",
        "hastaCinsiyet": "Kadın",
        "hastaTarih": "2018-01-25",
        "hastaTelefon": "+90(308)0628021",
        "hastaAdres": "4853 Cihandide Bypass\nSakaryaside, CO 26470",
        "hastaSifre": "bjess"
    },
    {
        "hastaID": 56,
        "hastaAdi": "Efil",
        "hastaSoyadi": "Seven",
        "hastaCinsiyet": "Kadın",
        "hastaTarih": "1927-05-02",
        "hastaTelefon": "+90(902)7248180",
        "hastaAdres": "4790 Abdulkadir Street Apt. 968\nKaradenizland, NE 25172",
        "hastaSifre": "lzwat"
    },
    {
        "hastaID": 57,
        "hastaAdi": "İncifir",
        "hastaSoyadi": "Yüksel",
        "hastaCinsiyet": "Kadın",
        "hastaTarih": "2009-12-28",
        "hastaTelefon": "(643)461 7634",
        "hastaAdres": "592 Aykut Harbor\nDemirside, ND 19942",
        "hastaSifre": "fe3vs"
    },
    {
        "hastaID": 58,
        "hastaAdi": "Aysoy",
        "hastaSoyadi": "Akçay",
        "hastaCinsiyet": "Kadın",
        "hastaTarih": "2009-02-18",
        "hastaTelefon": "(630)136 8322",
        "hastaAdres": "77462 Demir Shoals Apt. 514\nSakaryaberg, AR 66646",
        "hastaSifre": "xyebb"
    },
    {
        "hastaID": 59,
        "hastaAdi": "Gürarda",
        "hastaSoyadi": "Tevetoğlu",
        "hastaCinsiyet": "Kadın",
        "hastaTarih": "2001-07-15",
        "hastaTelefon": "+90 (604) 6077570",
        "hastaAdres": "0109 Demir Mountains\nSezerton, TN 36750",
        "hastaSifre": "bf4ps"
    },
    {
        "hastaID": 60,
        "hastaAdi": "Bişar",
        "hastaSoyadi": "Akçay",
        "hastaCinsiyet": "Kadın",
        "hastaTarih": "1955-08-28",
        "hastaTelefon": "+90(226)700-0761x1085",
        "hastaAdres": "39528 Tarhan Rapids Apt. 468\nWest Mukbileton, VA 63097",
        "hastaSifre": "mb37j"
    },
    {
        "hastaID": 61,
        "hastaAdi": "Bayruhan",
        "hastaSoyadi": "Yıldırım",
        "hastaCinsiyet": "Erkek",
        "hastaTarih": "1981-05-07",
        "hastaTelefon": "0519-448 8660",
        "hastaAdres": "4475 Ertaş Mount\nWest Gücal, PR 34839",
        "hastaSifre": "jfjsj"
    },
    {
        "hastaID": 62,
        "hastaAdi": "Yurtseven",
        "hastaSoyadi": "Şama",
        "hastaCinsiyet": "Erkek",
        "hastaTarih": "2008-07-17",
        "hastaTelefon": "949 5 048",
        "hastaAdres": "Unit 8919 Box 7788\nDPO AP 55968",
        "hastaSifre": "vojk3"
    },
    {
        "hastaID": 63,
        "hastaAdi": "Alparslan",
        "hastaSoyadi": "Sezgin",
        "hastaCinsiyet": "Erkek",
        "hastaTarih": "1990-05-22",
        "hastaTelefon": "+90(188)929-3764x5952",
        "hastaAdres": "66641 Yüksel Pines\nNew Celilayhaven, SC 14303",
        "hastaSifre": "qu4kr"
    },
    {
        "hastaID": 64,
        "hastaAdi": "Çopur",
        "hastaSoyadi": "Bilge",
        "hastaCinsiyet": "Kadın",
        "hastaTarih": "1942-01-29",
        "hastaTelefon": "+90 (551) 2292859",
        "hastaAdres": "653 Mestur Locks Apt. 343\nLake Sami, ND 87371",
        "hastaSifre": "otj79"
    },
    {
        "hastaID": 65,
        "hastaAdi": "Merba",
        "hastaSoyadi": "Alemdar",
        "hastaCinsiyet": "Kadın",
        "hastaTarih": "1996-05-15",
        "hastaTelefon": "02498802118",
        "hastaAdres": "07337 Güçlü Locks Apt. 355\nNew Özayview, ND 19310",
        "hastaSifre": "ucm8t"
    },
    {
        "hastaID": 66,
        "hastaAdi": "Rehime",
        "hastaSoyadi": "Soylu",
        "hastaCinsiyet": "Kadın",
        "hastaTarih": "1973-06-05",
        "hastaTelefon": "+90(235)124-4780x9719",
        "hastaAdres": "9399 Risalet Plaza Apt. 087\nZorlufurt, CO 26618",
        "hastaSifre": "pp10s"
    },
    {
        "hastaID": 67,
        "hastaAdi": "Ğanim",
        "hastaSoyadi": "Erdoğan",
        "hastaCinsiyet": "Kadın",
        "hastaTarih": "1974-02-27",
        "hastaTelefon": "0696 939 52 44",
        "hastaAdres": "Unit 4654 Box 7352\nDPO AA 42073",
        "hastaSifre": "pf11g"
    },
    {
        "hastaID": 68,
        "hastaAdi": "Ayülker",
        "hastaSoyadi": "Aksu",
        "hastaCinsiyet": "Kadın",
        "hastaTarih": "2012-05-22",
        "hastaTelefon": "+90(136)9686881",
        "hastaAdres": "97263 Zorlu Spurs\nNorth Eminfort, MD 12850",
        "hastaSifre": "2bcqa"
    },
    {
        "hastaID": 69,
        "hastaAdi": "Derkay",
        "hastaSoyadi": "Tevetoğlu",
        "hastaCinsiyet": "Erkek",
        "hastaTarih": "1974-02-25",
        "hastaTelefon": "(871)923 9682",
        "hastaAdres": "714 Özbay Square\nŞahdiyestad, WV 26187",
        "hastaSifre": "hpsyi"
    },
    {
        "hastaID": 70,
        "hastaAdi": "Akboğa",
        "hastaSoyadi": "Alemdar",
        "hastaCinsiyet": "Kadın",
        "hastaTarih": "1927-09-09",
        "hastaTelefon": "0066-909 0311",
        "hastaAdres": "666 Arsoy Island Apt. 205\nWest Âlemşah, WY 21591",
        "hastaSifre": "2iuut"
    },
    {
        "hastaID": 71,
        "hastaAdi": "Tuyuğ",
        "hastaSoyadi": "Öcalan",
        "hastaCinsiyet": "Erkek",
        "hastaTarih": "1964-04-13",
        "hastaTelefon": "0556 710 75 90",
        "hastaAdres": "1955 Ertaş Loaf\nMançofurt, OR 21595",
        "hastaSifre": "fmx71"
    },
    {
        "hastaID": 72,
        "hastaAdi": "Bilgen",
        "hastaSoyadi": "Demir",
        "hastaCinsiyet": "Kadın",
        "hastaTarih": "1986-08-12",
        "hastaTelefon": "+90 (365) 0417758",
        "hastaAdres": "58277 Atagün Circle\nErdoğanstad, HI 94901",
        "hastaSifre": "voqsp"
    },
    {
        "hastaID": 73,
        "hastaAdi": "Neyran",
        "hastaSoyadi": "Hayrioğlu",
        "hastaCinsiyet": "Kadın",
        "hastaTarih": "1927-12-14",
        "hastaTelefon": "+90 (510) 2104477",
        "hastaAdres": "262 Musaffa Curve\nYılmazshire, DE 49949",
        "hastaSifre": "80rsf"
    },
    {
        "hastaID": 74,
        "hastaAdi": "Çakar",
        "hastaSoyadi": "Yorulmaz",
        "hastaCinsiyet": "Kadın",
        "hastaTarih": "1944-09-09",
        "hastaTelefon": "153 6 231",
        "hastaAdres": "67343 Gücal Grove\nLake Veischester, TX 61493",
        "hastaSifre": "ow8gg"
    },
    {
        "hastaID": 75,
        "hastaAdi": "Süheyda",
        "hastaSoyadi": "Kısakürek",
        "hastaCinsiyet": "Kadın",
        "hastaTarih": "1976-07-18",
        "hastaTelefon": "0332 371 91 11",
        "hastaAdres": "417 Mürit River\nMançofort, AZ 47391",
        "hastaSifre": "y2o2j"
    },
    {
        "hastaID": 76,
        "hastaAdi": "Dirlik",
        "hastaSoyadi": "Gülen",
        "hastaCinsiyet": "Erkek",
        "hastaTarih": "1952-06-15",
        "hastaTelefon": "+90 (239) 8307641",
        "hastaAdres": "095 Yorulmaz Centers Suite 279\nKanpulatland, IL 52954",
        "hastaSifre": "f6cmc"
    },
    {
        "hastaID": 77,
        "hastaAdi": "Yolal",
        "hastaSoyadi": "Arslan",
        "hastaCinsiyet": "Erkek",
        "hastaTarih": "1967-04-28",
        "hastaTelefon": "(886)875 4361",
        "hastaAdres": "PSC 0008, Box 3890\nAPO AP 65543",
        "hastaSifre": "e2rc9"
    },
    {
        "hastaID": 78,
        "hastaAdi": "Nazlim",
        "hastaSoyadi": "Öcalan",
        "hastaCinsiyet": "Kadın",
        "hastaTarih": "2004-03-15",
        "hastaTelefon": "0746 405 60 23",
        "hastaAdres": "5429 Aksu Mountain\nYamanstad, VA 47123",
        "hastaSifre": "wzyo7"
    },
    {
        "hastaID": 79,
        "hastaAdi": "Hunalp",
        "hastaSoyadi": "Demirel",
        "hastaCinsiyet": "Kadın",
        "hastaTarih": "1965-11-25",
        "hastaTelefon": "0452 397 15 08",
        "hastaAdres": "073 Tarhan Stravenue\nAsimanland, KS 19196",
        "hastaSifre": "6p3uy"
    },
    {
        "hastaID": 80,
        "hastaAdi": "Özokçu",
        "hastaSoyadi": "Yüksel",
        "hastaCinsiyet": "Kadın",
        "hastaTarih": "1948-12-25",
        "hastaTelefon": "0299-357 1401",
        "hastaAdres": "322 Zülbiye Grove\nEast Zihniburgh, KY 40789",
        "hastaSifre": "sbfy4"
    },
    {
        "hastaID": 81,
        "hastaAdi": "Özüdoğru",
        "hastaSoyadi": "Güçlü",
        "hastaCinsiyet": "Kadın",
        "hastaTarih": "2011-02-18",
        "hastaTelefon": "(117)667 4615",
        "hastaAdres": "86911 Sezgin Springs\nRafiatown, DC 59102",
        "hastaSifre": "kppsx"
    },
    {
        "hastaID": 82,
        "hastaAdi": "Sevdi",
        "hastaSoyadi": "İnönü",
        "hastaCinsiyet": "Kadın",
        "hastaTarih": "1943-10-25",
        "hastaTelefon": "+90 (453) 1310032",
        "hastaAdres": "6733 Feza Throughway Suite 559\nÇamurcuoğlushire, NY 23115",
        "hastaSifre": "08wxx"
    },
    {
        "hastaID": 83,
        "hastaAdi": "Özdal",
        "hastaSoyadi": "Mansız",
        "hastaCinsiyet": "Erkek",
        "hastaTarih": "1948-02-22",
        "hastaTelefon": "0380-876 1570",
        "hastaAdres": "15585 Türkalp Plaza\nGülsüborough, MN 36012",
        "hastaSifre": "zezkk"
    },
    {
        "hastaID": 84,
        "hastaAdi": "Aydinç",
        "hastaSoyadi": "Durmuş",
        "hastaCinsiyet": "Kadın",
        "hastaTarih": "2002-05-16",
        "hastaTelefon": "0542-809 8726",
        "hastaAdres": "USNS Demir\nFPO AA 30718",
        "hastaSifre": "axoqz"
    },
    {
        "hastaID": 85,
        "hastaAdi": "Yekbun",
        "hastaSoyadi": "Sakarya",
        "hastaCinsiyet": "Kadın",
        "hastaTarih": "1980-09-29",
        "hastaTelefon": "(419)114 6302",
        "hastaAdres": "14847 Atanur Unions\nBilgenshire, AS 96699",
        "hastaSifre": "01t24"
    },
    {
        "hastaID": 86,
        "hastaAdi": "Erdibay",
        "hastaSoyadi": "Ülker",
        "hastaCinsiyet": "Erkek",
        "hastaTarih": "1913-07-24",
        "hastaTelefon": "+90(333)558-8567x6387",
        "hastaAdres": "814 Şafak Parkways Suite 470\nDurmuşburgh, UT 55323",
        "hastaSifre": "bb63l"
    },
    {
        "hastaID": 87,
        "hastaAdi": "Oğuzman",
        "hastaSoyadi": "Eraslan",
        "hastaCinsiyet": "Kadın",
        "hastaTarih": "1985-03-14",
        "hastaTelefon": "0217-814 4222",
        "hastaAdres": "978 Gönen Rapids\nPort Yalınton, PA 55872",
        "hastaSifre": "cxby2"
    },
    {
        "hastaID": 88,
        "hastaAdi": "Işın",
        "hastaSoyadi": "Bilgin",
        "hastaCinsiyet": "Kadın",
        "hastaTarih": "2004-03-31",
        "hastaTelefon": "+90(083)297-6927x351",
        "hastaAdres": "5753 Irıs Vista Suite 663\nSouth Söyler, MT 93203",
        "hastaSifre": "0litq"
    },
    {
        "hastaID": 89,
        "hastaAdi": "Narhanim",
        "hastaSoyadi": "Yıldırım",
        "hastaCinsiyet": "Kadın",
        "hastaTarih": "2005-12-31",
        "hastaTelefon": "487 1 751",
        "hastaAdres": "379 Efe Walk\nNew Uzsoyville, MD 50538",
        "hastaSifre": "neom4"
    },
    {
        "hastaID": 90,
        "hastaAdi": "Okbay",
        "hastaSoyadi": "Şafak",
        "hastaCinsiyet": "Erkek",
        "hastaTarih": "1991-08-01",
        "hastaTelefon": "+90 (760) 2316933",
        "hastaAdres": "78360 Aclan Knoll\nEast Paker, OR 93169",
        "hastaSifre": "ycd61"
    },
    {
        "hastaID": 91,
        "hastaAdi": "Ağmur",
        "hastaSoyadi": "Tarhan",
        "hastaCinsiyet": "Kadın",
        "hastaTarih": "2009-12-05",
        "hastaTelefon": "+90(945)040-8119x049",
        "hastaAdres": "85005 Feyzin Alley\nSouth Şuayp, MA 10909",
        "hastaSifre": "dkg4d"
    },
    {
        "hastaID": 92,
        "hastaAdi": "Cabir",
        "hastaSoyadi": "Şensoy",
        "hastaCinsiyet": "Erkek",
        "hastaTarih": "1923-09-26",
        "hastaTelefon": "+90 (861) 7491494",
        "hastaAdres": "86333 Fırat Mountains\nLake Basriyemouth, NH 82643",
        "hastaSifre": "vz8js"
    },
    {
        "hastaID": 93,
        "hastaAdi": "Süner",
        "hastaSoyadi": "Erdoğan",
        "hastaCinsiyet": "Kadın",
        "hastaTarih": "1923-11-18",
        "hastaTelefon": "+90(286)9185562",
        "hastaAdres": "15678 Sezer Falls\nIdıktown, ME 43159",
        "hastaSifre": "hpbv2"
    },
    {
        "hastaID": 94,
        "hastaAdi": "Durgadin",
        "hastaSoyadi": "Zorlu",
        "hastaCinsiyet": "Kadın",
        "hastaTarih": "2012-04-15",
        "hastaTelefon": "+90(826)615-7139x714",
        "hastaAdres": "074 Güçlü Place Suite 905\nUygunbury, NE 71045",
        "hastaSifre": "lpfso"
    },
    {
        "hastaID": 95,
        "hastaAdi": "Amaç",
        "hastaSoyadi": "Gülen",
        "hastaCinsiyet": "Erkek",
        "hastaTarih": "1987-09-26",
        "hastaTelefon": "905 9 556",
        "hastaAdres": "71007 Yurtseven Shoals Apt. 582\nYılmaztown, NC 66017",
        "hastaSifre": "0dd6i"
    },
    {
        "hastaID": 96,
        "hastaAdi": "Önel",
        "hastaSoyadi": "Ertaş",
        "hastaCinsiyet": "Erkek",
        "hastaTarih": "1958-05-22",
        "hastaTelefon": "05656438201",
        "hastaAdres": "22924 Yıldırım Mill Suite 226\nÇamurcuoğluview, CO 98400",
        "hastaSifre": "2oqq1"
    },
    {
        "hastaID": 97,
        "hastaAdi": "Oranlı",
        "hastaSoyadi": "Erdoğan",
        "hastaCinsiyet": "Kadın",
        "hastaTarih": "1994-11-03",
        "hastaTelefon": "636 9 554",
        "hastaAdres": "2652 Mehdiye Roads Suite 178\nSelaheddintown, ID 95811",
        "hastaSifre": "2wgm4"
    },
    {
        "hastaID": 98,
        "hastaAdi": "Nurdeniz",
        "hastaSoyadi": "Demirel",
        "hastaCinsiyet": "Erkek",
        "hastaTarih": "1909-05-10",
        "hastaTelefon": "+90(659)469-8999x6040",
        "hastaAdres": "09464 Bilge Lakes Suite 523\nNorth Gazel, PR 52460",
        "hastaSifre": "htuuj"
    },
    {
        "hastaID": 99,
        "hastaAdi": "Çelem",
        "hastaSoyadi": "Arslan",
        "hastaCinsiyet": "Erkek",
        "hastaTarih": "2022-02-11",
        "hastaTelefon": "+90 (267) 1802955",
        "hastaAdres": "USS Hayrioğlu\nFPO AP 42852",
        "hastaSifre": "edeny"
    },
    {
        "hastaID": 100,
        "hastaAdi": "Perinur",
        "hastaSoyadi": "Öcalan",
        "hastaCinsiyet": "Erkek",
        "hastaTarih": "1943-12-20",
        "hastaTelefon": "0810-729 9716",
        "hastaAdres": "6945 Uğur Forges\nSouth Gürelcemville, MI 18048",
        "hastaSifre": "dln9j"
    }
]